main.py
legacy_cobol_modernization-1.0.4.dist-info/licenses/LICENSE
legacy_cobol_modernization-1.0.4.dist-info/METADATA
legacy_cobol_modernization-1.0.4.dist-info/WHEEL
legacy_cobol_modernization-1.0.4.dist-info/entry_points.txt
legacy_cobol_modernization-1.0.4.dist-info/top_level.txt
legacy_cobol_modernization-1.0.4.dist-info/RECORD
