Metadata-Version: 2.4
Name: legacy-cobol-modernization
Version: 1.0.4
Summary: A Python implementation of a COBOL accounting system with Golden Master testing
Home-page: https://github.com/math974/modernize-legacy-cobol-app
Author: Your Name
Author-email: Your Name <your.email@example.com>
License: MIT
Project-URL: Homepage, https://github.com/math974/modernize-legacy-cobol-app
Project-URL: Bug Reports, https://github.com/math974/modernize-legacy-cobol-app/issues
Project-URL: Source, https://github.com/math974/modernize-legacy-cobol-app
Project-URL: Documentation, https://github.com/math974/modernize-legacy-cobol-app#readme
Keywords: cobol,legacy,modernization,golden-master,testing,accounting,migration,python
Classifier: Development Status :: 5 - Production/Stable
Classifier: Intended Audience :: Developers
Classifier: Topic :: Software Development :: Libraries :: Python Modules
Classifier: Topic :: Office/Business :: Financial :: Accounting
Classifier: License :: OSI Approved :: MIT License
Classifier: Programming Language :: Python :: 3
Classifier: Programming Language :: Python :: 3.8
Classifier: Programming Language :: Python :: 3.9
Classifier: Programming Language :: Python :: 3.10
Classifier: Programming Language :: Python :: 3.11
Classifier: Programming Language :: Python :: 3.12
Classifier: Operating System :: OS Independent
Requires-Python: >=3.8
License-File: LICENSE
Provides-Extra: dev
Requires-Dist: pytest>=7.4.0; extra == "dev"
Requires-Dist: pytest-cov>=4.1.0; extra == "dev"
Requires-Dist: ruff>=0.1.0; extra == "dev"
Requires-Dist: black>=23.0.0; extra == "dev"
Requires-Dist: mypy>=1.5.0; extra == "dev"
Provides-Extra: test
Requires-Dist: pytest>=7.4.0; extra == "test"
Requires-Dist: pytest-cov>=4.1.0; extra == "test"
Dynamic: author
Dynamic: home-page
Dynamic: license-file
Dynamic: requires-python
